Metadata-Version: 2.1
Name: timeagi
Version: 0.0.2
Summary: Time Series Foundation Model - TEMPO: Prompt-based Generative Pre-trained Transformer for Time Series Forecasting
Home-page: https://github.com/DC-research/TEMPO
Author: Defu Cao
Author-email: defucao@usc.edu
License: UNKNOWN
Project-URL: Bug Reports, https://github.com/DC-research/TEMPO/issues
Project-URL: Source, https://github.com/DC-research/TEMPO
Keywords: time-series,ml,llm
Platform: UNKNOWN
Classifier: Development Status :: 4 - Beta
Classifier: Intended Audience :: Developers
Classifier: License :: OSI Approved :: MIT License
Classifier: Programming Language :: Python :: 3.8
Requires-Python: >=3.7.2,<4
Requires-Dist: reformer-pytorch
Requires-Dist: patool
Requires-Dist: transformers
Requires-Dist: pandas
Requires-Dist: scikit-learn
Requires-Dist: matplotlib
Requires-Dist: statsmodels
Requires-Dist: numpy
Requires-Dist: torch==1.13.0
Requires-Dist: torchvision==0.14.0
Requires-Dist: torchaudio==0.13.0
Requires-Dist: peft
Requires-Dist: huggingface-hub
Requires-Dist: omegaconf
